{"cameraMode":{"drawMode":0,"name":"Shaded","section":"Shading Mode"},"sceneLighting":true,"audioPlay":false,"sceneViewState":{"showFog":true,"showMaterialUpdate":false,"showSkybox":true,"showFlares":true,"showImageEffects":true,"showParticleSystems":true},"in2DMode":false,"pivot":{"x":357.8123779296875,"y":-213.354736328125,"z":-93.00244140625},"rotation":{"x":0.03596185892820358,"y":-0.905017077922821,"z":0.4165918529033661,"w":0.07812493294477463},"size":449.63543701171877,"orthographic":false}